MANIFEST.in
README.md
requirements.txt
setup.py
heptapod_tests/__init__.py
heptapod_tests/access_levels.py
heptapod_tests/api.py
heptapod_tests/branch.py
heptapod_tests/config.py
heptapod_tests/constants.py
heptapod_tests/content.py
heptapod_tests/docker.py
heptapod_tests/fixtures.py
heptapod_tests/git.py
heptapod_tests/heptapod.py
heptapod_tests/hg.py
heptapod_tests/merge_request.py
heptapod_tests/namespace.py
heptapod_tests/project.py
heptapod_tests/project_mirror.py
heptapod_tests/requests_pool.py
heptapod_tests/reverse_calls.py
heptapod_tests/runner.py
heptapod_tests/selenium.py
heptapod_tests/session.py
heptapod_tests/ssh.py
heptapod_tests/user.py
heptapod_tests/utils.py
heptapod_tests/wait.py
heptapod_tests.egg-info/PKG-INFO
heptapod_tests.egg-info/SOURCES.txt
heptapod_tests.egg-info/dependency_links.txt
heptapod_tests.egg-info/requires.txt
heptapod_tests.egg-info/top_level.txt
run/README.md
tests/test_backups.py
tests/test_bookmarks.py
tests/test_ci.py
tests/test_clone_bundles.py
tests/test_closed_branch.py
tests/test_git.py
tests/test_groups.py
tests/test_hg_access.py
tests/test_import.py
tests/test_instance.py
tests/test_merge_requests.py
tests/test_multiple_heads.py
tests/test_project_mirror.py
tests/test_projects.py
tests/test_prune.py
tests/test_public.py
tests/test_publish.py
tests/test_pull.py
tests/test_push.py
tests/test_python_gitlab.py
tests/test_repo_files.py
tests/test_runner.py
tests/test_snippets.py
tests/test_ssh.py
tests/test_topics.py
tests/test_wikis.py