Metadata-Version: 2.1
Name: heptapod-tests
Version: 18.0.0
Summary: Heptapod Functional Tests
Home-page: https://foss.heptapod.net/heptapod/heptapod-tests
Author: octobus
Author-email: contact@octobus.net
License: GPL3+
Keywords: hg mercurial git heptapod gitlab selenium REST GraphQL
Requires-Dist: selenium
Requires-Dist: docker<4.3
Requires-Dist: PyYAML
